figrecipe/__init__.py
figrecipe/__main__.py
figrecipe/_branding.py
figrecipe/_graph.py
figrecipe/_graph_presets.py
figrecipe/_recorder.py
figrecipe/_recorder_utils.py
figrecipe/_seaborn.py
figrecipe/_serializer.py
figrecipe/_validator.py
figrecipe/plt.py
figrecipe/pyplot.py
figrecipe/utils.py
figrecipe/_api/__init__.py
figrecipe/_api/_extract.py
figrecipe/_api/_notebook.py
figrecipe/_api/_panel.py
figrecipe/_api/_plot.py
figrecipe/_api/_plot_helpers.py
figrecipe/_api/_save.py
figrecipe/_api/_save_helpers.py
figrecipe/_api/_seaborn_proxy.py
figrecipe/_api/_style_manager.py
figrecipe/_api/_subplots.py
figrecipe/_api/_validate.py
figrecipe/_api/_compose/__init__.py
figrecipe/_api/_compose/_freeform.py
figrecipe/_api/_compose/_grid.py
figrecipe/_api/_compose/_utils.py
figrecipe/_cli/__init__.py
figrecipe/_cli/_completion.py
figrecipe/_cli/_compose.py
figrecipe/_cli/_convert.py
figrecipe/_cli/_crop.py
figrecipe/_cli/_diagram.py
figrecipe/_cli/_edit.py
figrecipe/_cli/_extract.py
figrecipe/_cli/_fonts.py
figrecipe/_cli/_info.py
figrecipe/_cli/_main.py
figrecipe/_cli/_mcp.py
figrecipe/_cli/_plot.py
figrecipe/_cli/_reproduce.py
figrecipe/_cli/_style.py
figrecipe/_cli/_validate.py
figrecipe/_cli/_version.py
figrecipe/_composition/__init__.py
figrecipe/_composition/_alignment.py
figrecipe/_composition/_compose.py
figrecipe/_composition/_import_axes.py
figrecipe/_composition/_visibility.py
figrecipe/_dev/__init__.py
figrecipe/_dev/_plotters.py
figrecipe/_dev/_run_demos.py
figrecipe/_dev/browser/__init__.py
figrecipe/_dev/browser/_audio.py
figrecipe/_dev/browser/_caption.py
figrecipe/_dev/browser/_click_effect.py
figrecipe/_dev/browser/_cursor.py
figrecipe/_dev/browser/_highlight.py
figrecipe/_dev/browser/_narration.py
figrecipe/_dev/browser/_recorder.py
figrecipe/_dev/browser/_utils.py
figrecipe/_dev/browser/_video_trim/__init__.py
figrecipe/_dev/browser/_video_trim/_detection.py
figrecipe/_dev/browser/_video_trim/_markers.py
figrecipe/_dev/demo_plotters/__init__.py
figrecipe-0.18.0.dist-info/METADATA
figrecipe-0.18.0.dist-info/WHEEL
figrecipe-0.18.0.dist-info/entry_points.txt
figrecipe-0.18.0.dist-info/licenses/LICENSE
figrecipe-0.18.0.dist-info/RECORD
