Metadata-Version: 2.4
Name: figrecipe
Version: 0.18.0
Summary: Reproducible matplotlib wrapper with mm-precision layouts
Project-URL: Homepage, https://github.com/ywatanabe1989/figrecipe
Project-URL: Documentation, https://github.com/ywatanabe1989/figrecipe#readme
Project-URL: Repository, https://github.com/ywatanabe1989/figrecipe.git
Project-URL: Issues, https://github.com/ywatanabe1989/figrecipe/issues
Author-email: Yusuke Watanabe <ywatanabe@scitex.ai>
License-Expression: AGPL-3.0
License-File: LICENSE
Keywords: matplotlib,millimeter,plotting,publication,recipe,reproducibility,scientific,visualization,yaml
Classifier: Development Status :: 4 - Beta
Classifier: Intended Audience :: Science/Research
Classifier: License :: OSI Approved :: GNU Affero General Public License v3
Classifier: Operating System :: OS Independent
Classifier: Programming Language :: Python :: 3
Classifier: Programming Language :: Python :: 3.9
Classifier: Programming Language :: Python :: 3.10
Classifier: Programming Language :: Python :: 3.11
Classifier: Programming Language :: Python :: 3.12
Classifier: Topic :: Scientific/Engineering :: Visualization
Requires-Python: >=3.9
Requires-Dist: click>=8.0.0
Requires-Dist: matplotlib>=3.5.0
Requires-Dist: numpy>=1.20.0
Requires-Dist: rich>=13.0.0
Requires-Dist: ruamel-yaml>=0.17.0
Requires-Dist: scipy>=1.7.0
Provides-Extra: all
Requires-Dist: flask>=2.0.0; extra == 'all'
Requires-Dist: networkx>=3.0; extra == 'all'
Requires-Dist: pandas>=1.3.0; extra == 'all'
Requires-Dist: pillow>=9.0.0; extra == 'all'
Requires-Dist: playwright>=1.40.0; extra == 'all'
Requires-Dist: pytesseract>=0.3.0; extra == 'all'
Requires-Dist: pytest-cov>=4.0.0; extra == 'all'
Requires-Dist: pytest-xdist>=3.0.0; extra == 'all'
Requires-Dist: pytest>=7.0.0; extra == 'all'
Requires-Dist: pyvis>=0.3; extra == 'all'
Requires-Dist: pywebview>=4.0.0; extra == 'all'
Requires-Dist: pyyaml>=6.0.0; extra == 'all'
Requires-Dist: seaborn>=0.12.0; extra == 'all'
Provides-Extra: demo
Requires-Dist: playwright>=1.40.0; extra == 'demo'
Requires-Dist: pytesseract>=0.3.0; extra == 'demo'
Provides-Extra: desktop
Requires-Dist: flask>=2.0.0; extra == 'desktop'
Requires-Dist: pillow>=9.0.0; extra == 'desktop'
Requires-Dist: pyqt6-webengine>=6.0.0; extra == 'desktop'
Requires-Dist: pyqt6>=6.0.0; extra == 'desktop'
Requires-Dist: pywebview>=4.0.0; extra == 'desktop'
Requires-Dist: qtpy>=2.0.0; extra == 'desktop'
Provides-Extra: dev
Requires-Dist: pre-commit>=3.5.0; extra == 'dev'
Requires-Dist: pytest-cov>=4.0.0; extra == 'dev'
Requires-Dist: pytest-xdist>=3.0.0; extra == 'dev'
Requires-Dist: pytest>=7.0.0; extra == 'dev'
Requires-Dist: pyyaml>=6.0.0; extra == 'dev'
Provides-Extra: editor
Requires-Dist: flask>=2.0.0; extra == 'editor'
Requires-Dist: pillow>=9.0.0; extra == 'editor'
Provides-Extra: graph
Requires-Dist: networkx>=3.0; extra == 'graph'
Provides-Extra: graph-interactive
Requires-Dist: networkx>=3.0; extra == 'graph-interactive'
Requires-Dist: pyvis>=0.3; extra == 'graph-interactive'
Provides-Extra: imaging
Requires-Dist: pillow>=9.0.0; extra == 'imaging'
Provides-Extra: mcp
Requires-Dist: fastmcp>=2.0.0; extra == 'mcp'
Provides-Extra: seaborn
Requires-Dist: pandas>=1.3.0; extra == 'seaborn'
Requires-Dist: seaborn>=0.12.0; extra == 'seaborn'
